QGEval_metrics/MoverScore.py
QGEval_metrics/__init__.py
QGEval_metrics/base_evaluator.py
QGEval_metrics/coeff.py
QGEval_metrics/geval.py
QGEval_metrics/gptscore.py
QGEval_metrics/metrics.py
QGEval_metrics/prompt_gpt.py
QGEval_metrics/qrel.py
QGEval_metrics/qsts.py
QGEval_metrics/test_bleurt.py
QGEval_metrics/BARTScore/LICENSE
QGEval_metrics/BARTScore/README.md
QGEval_metrics/BARTScore/analysis.ipynb
QGEval_metrics/BARTScore/analysis.py
QGEval_metrics/BARTScore/bart_score.py
QGEval_metrics/BARTScore/requirements.txt
QGEval_metrics/BARTScore/t5-11b.py
QGEval_metrics/BARTScore/test.py
QGEval_metrics/BARTScore/utils.py
QGEval_metrics/BARTScore/__pycache__/bart_score.cpython-37.pyc
QGEval_metrics/BARTScore/__pycache__/bart_score.cpython-39.pyc
QGEval_metrics/BARTScore/train/README.md
QGEval_metrics/BARTScore/train/args.py
QGEval_metrics/BARTScore/train/bart.py
QGEval_metrics/BARTScore/train/reproduce/args.py
QGEval_metrics/BARTScore/train/reproduce/bart.py
QGEval_metrics/BARTScore/train/reproduce/finetune.py
QGEval_metrics/BARTScore/train/reproduce/utils.py
QGEval_metrics/BARTScore/train/reproduce/data/README.md
QGEval_metrics/BARTScore/train/reproduce/models/__init__.py
QGEval_metrics/BARTScore/train/reproduce/models/bart_utils.py
QGEval_metrics/GPTScore/.gitignore
QGEval_metrics/GPTScore/README.md
QGEval_metrics/GPTScore/flan_score.py
QGEval_metrics/GPTScore/gpt3_score.py
QGEval_metrics/GPTScore/gpt_inference.py
QGEval_metrics/GPTScore/opt_score.py
QGEval_metrics/GPTScore/score_d2t.py
QGEval_metrics/GPTScore/utils.py
QGEval_metrics/QBLEU/.DS_Store
QGEval_metrics/QBLEU/.gitignore
QGEval_metrics/QBLEU/README.md
QGEval_metrics/QBLEU/__init__.py
QGEval_metrics/QBLEU/answerability_score.py
QGEval_metrics/QBLEU/avg_std.py
QGEval_metrics/QBLEU/setup.py
QGEval_metrics/QBLEU/annotated-questions/squad.tsv
QGEval_metrics/QBLEU/annotated-questions/vqa.tsv
QGEval_metrics/QBLEU/annotated-questions/wikimovies.tsv
QGEval_metrics/QBLEU/bleu/LICENSE
QGEval_metrics/bleurt/BLEURT.egg-info/PKG-INFO
QGEval_metrics/bleurt/BLEURT.egg-info/SOURCES.txt
QGEval_metrics/bleurt/BLEURT.egg-info/dependency_links.txt
QGEval_metrics/bleurt/BLEURT.egg-info/requires.txt
QGEval_metrics/bleurt/BLEURT.egg-info/top_level.txt
QGEval_metrics-1.1.0.dist-info/LICENSE
QGEval_metrics-1.1.0.dist-info/METADATA
QGEval_metrics-1.1.0.dist-info/WHEEL
QGEval_metrics-1.1.0.dist-info/top_level.txt
QGEval_metrics-1.1.0.dist-info/RECORD
