Metadata-Version: 2.1
Name: QGEval-metrics
Version: 1.1.0
Summary: Auto metrics for evaluating generated questions
Home-page: https://github.com/WeipingFu/QGEval/tree/main
Author: WeipingFu
Author-email: fuweiping1993@foxmail.com
Classifier: Development Status :: 5 - Production/Stable
Classifier: Intended Audience :: Science/Research
Classifier: License :: OSI Approved :: Apache Software License
Classifier: Operating System :: OS Independent
Classifier: Programming Language :: Python
Classifier: Programming Language :: Python :: 3
Classifier: Programming Language :: Python :: 3.7
Classifier: Programming Language :: Python :: 3.8
Classifier: Programming Language :: Python :: 3.9
Classifier: Programming Language :: Python :: 3.10
Classifier: Programming Language :: Python :: 3.11
Classifier: Topic :: Database
Requires-Python: >=3.7
License-File: LICENSE
Requires-Dist: transformers >=4.17.0.dev0
Requires-Dist: accelerate
Requires-Dist: datasets >=1.8.0
Requires-Dist: sentencepiece !=0.1.92
Requires-Dist: protobuf
Requires-Dist: rouge-score
Requires-Dist: nltk
Requires-Dist: py7zr
Requires-Dist: torch >=1.3
Requires-Dist: evaluate
Requires-Dist: prettytable
Requires-Dist: tqdm
Requires-Dist: openai
Requires-Dist: openpyxl
Requires-Dist: stanza
